conva_ai/__init__.py
conva_ai/async_client.py
conva_ai/base.py
conva_ai/client.py
conva_ai/context.py
conva_ai/response.py
conva_ai-0.2.4.dist-info/METADATA
conva_ai-0.2.4.dist-info/WHEEL
conva_ai-0.2.4.dist-info/top_level.txt
conva_ai-0.2.4.dist-info/RECORD
