Metadata-Version: 2.1
Name: conva_ai
Version: 0.2.4
Summary: Python SDK for using Conva AI co-pilots
Author-email: Slang Labs <support@slanglabs.in>
Project-URL: Homepage, http://www.slanglabs.in
Project-URL: Documentation, https://docs.slanglabs.in/
Classifier: Programming Language :: Python :: 3
Classifier: License :: OSI Approved :: MIT License
Classifier: Operating System :: OS Independent
Requires-Python: >=3.10
Requires-Dist: annotated-types ==0.6.0
Requires-Dist: anyio ==4.4.0
Requires-Dist: certifi ==2024.2.2
Requires-Dist: h11 ==0.14.0
Requires-Dist: httpcore ==1.0.5
Requires-Dist: httpx ==0.27.0
Requires-Dist: idna ==3.7
Requires-Dist: pydantic ==2.7.0
Requires-Dist: pydantic-core ==2.18.1
Requires-Dist: sniffio ==1.3.1
Requires-Dist: sseclient-py ==1.8.0
Requires-Dist: typing-extensions ==4.11.0
